setup.py
asnhistory/__init__.py
asnhistory/api.py
asnhistory.egg-info/PKG-INFO
asnhistory.egg-info/SOURCES.txt
asnhistory.egg-info/dependency_links.txt
asnhistory.egg-info/requires.txt
asnhistory.egg-info/top_level.txt