Metadata-Version: 1.1
Name: asnhistory
Version: 2.0.4
Summary: Query a redis database to access to the ASNs descriptions.
Home-page: https://github.com/Rafiot/ASN-Description-History
Author: Raphaël Vinot
Author-email: raphael.vinot@circl.lu
License: UNKNOWN
Platform: UNKNOWN
Classifier: License :: OSI Approved :: GNU General Public License v3 (GPLv3)
Classifier: Development Status :: 5 - Production/Stable
Classifier: Environment :: Console
Classifier: Intended Audience :: Science/Research
Classifier: Intended Audience :: Telecommunications Industry
Classifier: Programming Language :: Python :: 2.7
Classifier: Programming Language :: Python :: 3
Classifier: Topic :: Security
Classifier: Topic :: Internet
